tree_sitter_cfengine/__init__.py
tree_sitter_cfengine/__init__.pyi
tree_sitter_cfengine/_binding.pyd
tree_sitter_cfengine/binding.c
tree_sitter_cfengine/py.typed
tree_sitter_cfengine-1.0.12.dist-info/licenses/LICENSE
tree_sitter_cfengine-1.0.12.dist-info/METADATA
tree_sitter_cfengine-1.0.12.dist-info/WHEEL
tree_sitter_cfengine-1.0.12.dist-info/top_level.txt
tree_sitter_cfengine-1.0.12.dist-info/RECORD
