Metadata-Version: 2.4
Name: tree-sitter-cfengine
Version: 1.0.12
Summary: CFEngine grammar for tree-sitter
Author-email: Ole Herman Schumacher Elgesem <oleherman93@gmail.com>
License: MIT
Project-URL: Homepage, https://github.com/olehermanse/tree-sitter-cfengine
Keywords: incremental,parsing,tree-sitter,cfengine
Classifier: Intended Audience :: Developers
Classifier: License :: OSI Approved :: MIT License
Classifier: Topic :: Software Development :: Compilers
Classifier: Topic :: Text Processing :: Linguistic
Classifier: Typing :: Typed
Requires-Python: >=3.9
License-File: LICENSE
Provides-Extra: core
Requires-Dist: tree-sitter~=0.23; extra == "core"
Dynamic: license-file
